ronin/__init__.py
ronin/cli.py
ronin/contexts.py
ronin/executors.py
ronin/extensions.py
ronin/ninja.py
ronin/phases.py
ronin/projects.py
ronin/version.py
ronin/binutils/__init__.py
ronin/files/__init__.py
ronin/gcc/__init__.py
ronin/go/__init__.py
ronin/java/__init__.py
ronin/pkg_config/__init__.py
ronin/qt/__init__.py
ronin/rust/__init__.py
ronin/sdl/__init__.py
ronin/utils/__init__.py
ronin/utils/argparse.py
ronin/utils/collections.py
ronin/utils/compat.py
ronin/utils/messages.py
ronin/utils/paths.py
ronin/utils/platform.py
ronin/utils/strings.py
ronin/utils/types.py
ronin/vala/__init__.py
ronin-1.1.1.dist-info/DESCRIPTION.rst
ronin-1.1.1.dist-info/METADATA
ronin-1.1.1.dist-info/RECORD
ronin-1.1.1.dist-info/WHEEL
ronin-1.1.1.dist-info/metadata.json
ronin-1.1.1.dist-info/top_level.txt
