Metadata-Version: 2.0
Name: ronin
Version: 1.1.1
Summary: Rōnin
Home-page: https://github.com/tliron/ronin
Author: Tal Liron
Author-email: tal.liron@gmail.com
License: Apache License Version 2.0
Platform: UNKNOWN
Classifier: Development Status :: 5 - Production/Stable
Classifier: Environment :: Console
Classifier: Intended Audience :: Developers
Classifier: License :: OSI Approved :: Apache Software License
Classifier: Operating System :: OS Independent
Classifier: Programming Language :: Python
Classifier: Topic :: Software Development :: Build Tools
Requires-Dist: blessings (<2.0,>=1.6)
Requires-Dist: colorama (<2.0.0,>=0.3.9)
Requires-Dist: glob2 (<=2.0,>=0.5)
